nanome_matryx/Matryx.py
nanome_matryx/MatryxCortex.py
nanome_matryx/__init__.py
nanome_matryx/blockies.py
nanome_matryx/utils.py
nanome_matryx/components/Calendar.py
nanome_matryx/components/json/calendar.json
nanome_matryx/components/json/crumb.json
nanome_matryx/components/json/crumbs.json
nanome_matryx/contracts/MatryxCommit.py
nanome_matryx/contracts/MatryxPlatform.py
nanome_matryx/contracts/MatryxToken.py
nanome_matryx/contracts/MatryxTournament.py
nanome_matryx/contracts/Web3Helper.py
nanome_matryx/images/MatryxLogoBlack.png
nanome_matryx/images/MatryxLogoOpaque.png
nanome_matryx/images/MatryxLogoWhite.png
nanome_matryx/images/addAccount.png
nanome_matryx/images/arrow.png
nanome_matryx/images/checkmark.png
nanome_matryx/images/settings.png
nanome_matryx/images/withdrawMTX.png
nanome_matryx/menus/AccountsMenu.py
nanome_matryx/menus/Confirm.py
nanome_matryx/menus/CreateTournamentMenu.py
nanome_matryx/menus/CreationMenu.py
nanome_matryx/menus/CreationsMenu.py
nanome_matryx/menus/FilesMenu.py
nanome_matryx/menus/FirstToHashMenu.py
nanome_matryx/menus/MainMenu.py
nanome_matryx/menus/Modal.py
nanome_matryx/menus/SettingsMenu.py
nanome_matryx/menus/TournamentMenu.py
nanome_matryx/menus/json/accounts.json
nanome_matryx/menus/json/confirm.json
nanome_matryx/menus/json/create_submission.json
nanome_matryx/menus/json/create_tournament.json
nanome_matryx/menus/json/creation.json
nanome_matryx/menus/json/files.json
nanome_matryx/menus/json/firsttohash.json
nanome_matryx/menus/json/manage.json
nanome_matryx/menus/json/matryx.json
nanome_matryx/menus/json/modal.json
nanome_matryx/menus/json/my_creations.json
nanome_matryx/menus/json/settings.json
nanome_matryx/menus/json/submission.json
nanome_matryx/menus/json/tournament.json
nanome_matryx/menus/json/view_file.json
nanome_matryx/menus/json/select_winners/options.json
nanome_matryx/menus/json/select_winners/select_winners.json
nanome_matryx/menus/json/select_winners/update_round.json
nanome_matryx-0.0.1.dist-info/LICENSE
nanome_matryx-0.0.1.dist-info/METADATA
nanome_matryx-0.0.1.dist-info/WHEEL
nanome_matryx-0.0.1.dist-info/entry_points.txt
nanome_matryx-0.0.1.dist-info/top_level.txt
nanome_matryx-0.0.1.dist-info/RECORD
